llamao/__init__.py
llamao-0.0.1.dist-info/METADATA
llamao-0.0.1.dist-info/WHEEL
llamao-0.0.1.dist-info/licenses/LICENSE
llamao-0.0.1.dist-info/RECORD
