Metadata-Version: 2.1
Name: llamao
Version: 0.0.1
Summary: LLM helpers and examples
Project-URL: Homepage, https://github.com/jaychia/llmao
Project-URL: Issues, https://github.com/jaychia/llmao/issues
Author-email: Jay Chia <jaychia94@gmail.com>
License-File: LICENSE
Classifier: License :: OSI Approved :: Apache Software License
Classifier: Operating System :: OS Independent
Classifier: Programming Language :: Python :: 3
Requires-Python: >=3.8
